bmi/__init__.py
bmi/benchmark/__init__.py
bmi/benchmark/result.py
bmi/benchmark/task.py
bmi/benchmark/task_list.py
bmi/benchmark/tasks/__init__.py
bmi/benchmark/tasks/additive_noise.py
bmi/benchmark/tasks/asinh.py
bmi/benchmark/tasks/bimodal_gaussians.py
bmi/benchmark/tasks/bivariate_normal.py
bmi/benchmark/tasks/embeddings.py
bmi/benchmark/tasks/half_cube.py
bmi/benchmark/tasks/mixtures.py
bmi/benchmark/tasks/multinormal.py
bmi/benchmark/tasks/normal_cdf.py
bmi/benchmark/tasks/power.py
bmi/benchmark/tasks/rotate.py
bmi/benchmark/tasks/scaling.py
bmi/benchmark/tasks/spiral.py
bmi/benchmark/tasks/student.py
bmi/benchmark/tasks/wiggly.py
bmi/benchmark/utils/__init__.py
bmi/benchmark/utils/dict_dumper.py
bmi/benchmark/utils/timer.py
bmi/estimators/__init__.py
bmi/estimators/_histogram.py
bmi/estimators/_kde.py
bmi/estimators/base.py
bmi/estimators/correlation.py
bmi/estimators/external/__init__.py
bmi/estimators/external/external_estimator.py
bmi/estimators/external/gmm.py
bmi/estimators/external/julia_estimators.py
bmi/estimators/external/r_estimators.py
bmi/estimators/function_wrapper.py
bmi/estimators/ksg.py
bmi/estimators/neural/__init__.py
bmi/estimators/neural/_backend_linear_memory.py
bmi/estimators/neural/_backend_quadratic_memory.py
bmi/estimators/neural/_basic_training.py
bmi/estimators/neural/_critics.py
bmi/estimators/neural/_estimators.py
bmi/estimators/neural/_mine_estimator.py
bmi/estimators/neural/_training_log.py
bmi/estimators/neural/_types.py
bmi/interface.py
bmi/plot_utils/__init__.py
bmi/plot_utils/subplots_from_axsize.py
bmi/samplers/__init__.py
bmi/samplers/_additive_uniform.py
bmi/samplers/_discrete_continuous.py
bmi/samplers/_independent_coordinates.py
bmi/samplers/_matrix_utils.py
bmi/samplers/_split_student_t.py
bmi/samplers/_splitmultinormal.py
bmi/samplers/_tfp/__init__.py
bmi/samplers/_tfp/_core.py
bmi/samplers/_tfp/_normal.py
bmi/samplers/_tfp/_product.py
bmi/samplers/_tfp/_student.py
bmi/samplers/_tfp/_wrapper.py
benchmark_mi-0.1.3.dist-info/LICENSE
benchmark_mi-0.1.3.dist-info/METADATA
benchmark_mi-0.1.3.dist-info/WHEEL
benchmark_mi-0.1.3.dist-info/RECORD
