Metadata-Version: 2.1
Name: benchmark-mi
Version: 0.1.3
Summary: Estimators of mutual information and distributions used to benchmark them.
License: MIT
Author: Paweł Czyż
Author-email: pawelpiotr.czyz@ai.ethz.ch
Requires-Python: >=3.9,<3.13
Classifier: License :: OSI Approved :: MIT License
Classifier: Programming Language :: Python :: 3
Classifier: Programming Language :: Python :: 3.9
Classifier: Programming Language :: Python :: 3.10
Classifier: Programming Language :: Python :: 3.11
Requires-Dist: equinox (>=0.10.2,<0.11.0)
Requires-Dist: jax (>=0.4.8,<0.5.0)
Requires-Dist: jaxlib (>=0.4.7,<0.5.0)
Requires-Dist: numpy (>=1.24.2,<2.0.0)
Requires-Dist: optax (>=0.1.4,<0.2.0)
Requires-Dist: pandas (>=1.5.3,<2.0.0)
Requires-Dist: pydantic (>=1.10.7,<2.0.0)
Requires-Dist: pyyaml (>=6.0,<7.0)
Requires-Dist: scikit-learn (>=1.2.2,<2.0.0)
Requires-Dist: scipy (>=1.10.1,<2.0.0)
Requires-Dist: tensorflow-probability[jax] (>=0.20.1,<0.21.0)
Requires-Dist: tqdm (>=4.64.1,<5.0.0)
